tooth/__init__.py
tooth/__main__.py
tooth/main.py
tooth_python-0.1.5.dist-info/METADATA
tooth_python-0.1.5.dist-info/WHEEL
tooth_python-0.1.5.dist-info/entry_points.txt
tooth_python-0.1.5.dist-info/top_level.txt
tooth_python-0.1.5.dist-info/RECORD
