Metadata-Version: 2.4
Name: tooth-python
Version: 0.1.5
Summary: Generating text.
Maintainer: Cheesecake2960
License-Expression: CC0-1.0
Project-URL: Repository, https://github.com/Cheesecake2960/tooth.git
Project-URL: Issues, https://github.com/Cheesecake2960/tooth/issues
Keywords: generate,tooth
Classifier: Programming Language :: Python
Requires-Python: >=3.8
